WebsocketServer/CLI.py
WebsocketServer/WebsocketServer.py
WebsocketServer/__init__.py
websocketserverlibrary-0.1.0.dist-info/METADATA
websocketserverlibrary-0.1.0.dist-info/WHEEL
websocketserverlibrary-0.1.0.dist-info/top_level.txt
websocketserverlibrary-0.1.0.dist-info/RECORD
