Metadata-Version: 2.4
Name: WebsocketServerLibrary
Version: 0.1.0
Summary: A websocket server interface. Easy to use.
Author: Erri4
Project-URL: Homepage, https://github.com/erri4/WebsocketServer
Project-URL: Bug Tracker, https://github.com/erri4/WebsocketServer/issues
Requires-Python: >=3.8
